LICENSE.rst
README.md
setup.py
the_directory_scanner/__init__.py
the_directory_scanner/main.py
the_directory_scanner.egg-info/PKG-INFO
the_directory_scanner.egg-info/SOURCES.txt
the_directory_scanner.egg-info/dependency_links.txt
the_directory_scanner.egg-info/top_level.txt