Metadata-Version: 2.1
Name: the-directory-scanner
Version: 1.0
Summary: The Directory Scanner is a Python library designed to simplify the process of scanning directory structures and generating a comprehensive list of files and folders. It provides a convenient way to recursively traverse directories, ignoring specific files and folders specified by the user.
Home-page: https://github.com/Armen-Jean-Andreasian
Author: Armen-Jean Andreasian
Author-email: armen_andreasian@proton.me
License: BSD
Keywords: directory structure,python
Classifier: Development Status :: 3 - Alpha
Classifier: Intended Audience :: Developers
Classifier: Topic :: Software Development :: Libraries :: Python Modules
Classifier: Programming Language :: Python :: 3
Classifier: License :: OSI Approved :: BSD License
Classifier: Operating System :: OS Independent
Requires-Python: >=3.8
License-File: LICENSE.rst
